llm_topology.py
llm_topology-0.1.dist-info/LICENSE
llm_topology-0.1.dist-info/METADATA
llm_topology-0.1.dist-info/WHEEL
llm_topology-0.1.dist-info/entry_points.txt
llm_topology-0.1.dist-info/top_level.txt
llm_topology-0.1.dist-info/RECORD
