Metadata-Version: 2.1
Name: llm-topology
Version: 0.1
Summary: LLM access to Topology
Author: Nick Mystic
License: Apache-2.0
Project-URL: Homepage, https://github.com/ghostofpokemon/llm-topology
Project-URL: Changelog, https://github.com/ghostofpokemon/llm-topology/releases
Project-URL: Issues, https://github.com/ghostofpokemon/llm-topology/issues
Project-URL: CI, https://github.com/ghostofpokemon/llm-topology/actions
Classifier: License :: OSI Approved :: Apache Software License
License-File: LICENSE
Requires-Dist: llm
Provides-Extra: test
Requires-Dist: pytest ; extra == 'test'
Requires-Dist: pytest-recording ; extra == 'test'
